Workbook
Name IQ_CH: 110000
Name IQ_CQ: 5000
Name IQ_CY: 10000
Name IQ_DAILY: 500000
Name IQ_FH: 100000
Name IQ_FQ: 500
Name IQ_FY: 1000
Name IQ_LTM: 2000
Name IQ_MONTH: 15000
Name IQ_NTM: 6000
Name IQ_WEEK: 50000
Name IQ_YTD: 3000

Sheet <intro>

Sheet MSCI Europe Net Index EUR End o
A1: MSCI Europe Net Index EUR End of Day | Index Constituents Analysis 30-Nov-2020 10:09
A3: Index Constituents Analysis
A4: Report: Index Constituents & Weights
A5: 1 - 434 of 434
A6: Name | B6: RIC | C6: Open | D6: Ccy | E6: Foreign Inclusion Factor | F6: Domestic Inclusion Factor | G6: Index Shares | H6: Weight % | I6: Mcap (USD) | J6: ISIN | K6: Ticker
A7: Telecom Italia SpA | B7: TLITn.MI | C7: 0.4287 | D7: EUR | E7: 1 | F7: 1 | G7: 6027791699 | H7: 0.032487699 | I7: 3.087629e+09
A8: Metro AG | B8: B4B.DE | C8: 7.86 | D8: EUR | E8: 0.5 | F8: 0.5 | G8: 180060868 | H8: 0.017792998 | I8: 3.3820908e+09
A9: SES SA | B9: SESFd.PA | C9: 7.9 | D9: EUR | E9: 1 | F9: 1 | G9: 383457600 | H9: 0.0380848 | I9: 3.6195771e+09
A10: Bayerische Motoren Werke AG | B10: BMWG_p.DE | C10: 55.5 | D10: EUR | E10: 1 | F10: 1 | G10: 56867304 | H10: 0.039679196 | I10: 3.7711083e+09
A11: Fuchs Petrolub SE | B11: FPEG_p.DE | C11: 48.26 | D11: EUR | E11: 1 | F11: 1 | G11: 69500000 | H11: 0.042167646 | I11: 4.0076105e+09
A12: Leonardo SpA | B12: LDOF.MI | C12: 5.986 | D12: EUR | E12: 0.7 | F12: 0.7 | G12: 4.0470528e+08 | H12: 0.030456698 | I12: 4.1351468e+09
A13: thyssenkrupp AG | B13: TKAG.DE | C13: 5.564 | D13: EUR | E13: 0.65 | F13: 0.65 | G13: 4.0464563e+08 | H13: 0.028305395 | I13: 4.1386815e+09
A14: Andritz AG | B14: ANDR.VI | C14: 34.94 | D14: EUR | E14: 0.7 | F14: 0.7 | G14: 72800000 | H14: 0.031978752 | I14: 4341798136
A15: Bankinter SA | B15: BKT.MC | C15: 4.174 | D15: EUR | E15: 0.75 | F15: 0.75 | G15: 6.7414962e+08 | H15: 0.03537659 | I15: 4.4829187e+09
A16: JCDecaux SA | B16: JCDX.PA | C16: 17.89 | D16: EUR | E16: 0.4 | F16: 0.4 | G16: 85161124 | H16: 0.019153977 | I16: 4.550982e+09
A17: Telenet Group Holding NV | B17: TNET.BR | C17: 35.06 | D17: EUR | E17: 0.4 | F17: 0.4 | G17: 45498778 | H17: 0.020054825 | I17: 4.7650235e+09
A18: Eurazeo SE | B18: EURA.PA | C18: 52 | D18: EUR | E18: 0.5 | F18: 0.5 | G18: 39314622 | H18: 0.025701867 | I18: 4.8854079e+09
... A440: Nestle SA | B440: NESN.S | C440: 102.3 | D440: CHF | E440: 1 | F440: 1 | G440: 2976000000 | H440: 3.5403795 | I440: 3.3647745e+11
A441: 1 - 434 of 434

Sheet STOXX 600
A1: =TODAY() -> 44263 | B1: Name | C1: Adj Price | D1: Max | E1: Min | F1: Var | G1: Var% | H1: Vol | I1: Hour | J1: ISIN | K1: Ticker
B2: 3I Group | C2: 1.147,50 | D2: 1.151,00 | E2: 1.126,50 | F2: 12 | G2: 0.0106 | H2: 1,16M | I2: 0.73263889
B3: A2A | C3: 1.426 | D3: 1.436 | E3: 1.386 | F3: 0.04 | G3: 0.0289 | H3: 12,78M | I3: 0.73292824
B4: AAK | C4: 186.1 | D4: 188.7 | E4: 185.2 | F4: -0.7 | G4: -0.0035 | H4: 502,63K | I4: 0.72905093
B5: Aalberts Industries | C5: 40.7 | D5: 40.74 | E5: 39.77 | F5: 1.36 | G5: 0.0346 | H5: 289,16K | I5: 0.73483796
B6: ABB | C6: 28.27 | D6: 28.27 | E6: 27.35 | F6: 1.21 | G6: 0.0447 | H6: 8,66M | I6: 0.73081019
B7: ABN AMRO | C7: 10.74 | D7: 10.75 | E7: 9.96 | F7: 0.9 | G7: 0.0915 | H7: 10,54M | I7: 0.73453704
B8: Accor | C8: 34.77 | D8: 35 | E8: 34.14 | F8: 0.64 | G8: 0.0188 | H8: 1,52M | I8: 0.73328704
B9: Ackermans en van Haaren | C9: 133.8 | D9: 135.8 | E9: 133.5 | F9: 0.9 | G9: 0.0068 | H9: 27,58K | I9: 0.73327546
B10: ACS | C10: 26.49 | D10: 26.62 | E10: 26.035 | F10: 0.36 | G10: 0.0138 | H10: 311,75K | I10: 0.73261574
B11: Adecco N | C11: 63.78 | D11: 63.78 | E11: 61.88 | F11: 1.92 | G11: 0.031 | H11: 845,38K | I11: 0.72959491
B12: Adidas | C12: 280.06 | D12: 282.06 | E12: 271.65 | F12: 7.86 | G12: 0.0289 | H12: 459,19K | I12: 0.72899306
B13: Admiral Group | C13: 2.932,0 | D13: 2.967,0 | E13: 2.879,0 | F13: -27 | G13: -0.0091 | H13: 606,71K | I13: 0.73263889
B14: ADO Properties SARL | C14: 23.64 | D14: 23.84 | E14: 23.16 | F14: 0.4 | G14: 0.0172 | H14: 179,47K | I14: 0.72847222
B15: Adyen | C15: 1.860,00 | D15: 1.868,00 | E15: 1.785,50 | F15: 46 | G15: 0.0254 | H15: 82,37K | I15: 0.73320602
B16: Aedifica | C16: 96.3 | D16: 97.9 | E16: 96.1 | F16: -0.9 | G16: -0.0093 | H16: 68,31K | I16: 0.73283565
B17: Aegon NV | C17: 4.273 | D17: 4.304 | E17: 4.096 | F17: 0.199 | G17: 0.0488 | H17: 15,78M | I17: 0.73454861
B18: Aena | C18: 145.9 | D18: 146.45 | E18: 141.3 | F18: 6.3 | G18: 0.0451 | H18: 72,94K | I18: 0.73258102
B19: Aeroports Paris | C19: 105.5 | D19: 108.1 | E19: 103.5 | F19: 0.5 | G19: 0.0048 | H19: 145,85K | I19: 0.73277778
B20: AF AB | C20: 236 | D20: 236 | E20: 231.6 | F20: 4.6 | G20: 0.0199 | H20: 181,62K | I20: 0.72905093
B21: Ageas SA | C21: 50.92 | D21: 51.12 | E21: 50.38 | F21: 0.66 | G21: 0.0131 | H21: 626,39K | I21: 0.73357639
B22: Aggreko | C22: 889 | D22: 897 | E22: 883.5 | F22: -6 | G22: -0.0067 | H22: 1,23M | I22: 0.73263889
B23: Ahold Delhaize | C23: 22.5 | D23: 22.59 | E23: 22.24 | F23: 0.01 | G23: 0.0004 | H23: 3,63M | I23: 0.73538194
B24: AIB | C24: 1.948 | D24: 1.951 | E24: 1.85 | F24: 0.083 | G24: 0.0445 | H24: 2,83M | I24: 0.72005787
B25: Air France KLM SA | C25: 5.32 | D25: 5.36 | E25: 5.19 | F25: 0.14 | G25: 0.0274 | H25: 4,15M | I25: 0.73381944
B26: Air Liquide | C26: 130.85 | D26: 131.45 | E26: 127.5 | F26: 3.4 | G26: 0.0267 | H26: 1,12M | I26: 0.7343287
B27: Airbus Group | C27: 100.52 | D27: 100.68 | E27: 96.27 | F27: 5.1 | G27: 0.0534 | H27: 2,65M | I27: 0.73274306
... B37: Alten | C37: 95.4 | D37: 97.85 | E37: 93.1 | F37: 3 | G37: 0.0325 | H37: 66,98K | I37: 0.73265046
B38: Altice | C38: 5.34 | D38: 5.35 | E38: 5.32 | F38: 0 | G38: 0 | H38: 0 | I38: 44222
B39: Amadeus | C39: 60.06 | D39: 61.46 | E39: 59.78 | F39: 0.89 | G39: 0.015 | H39: 512,60K | I39: 0.7287963
B40: Ambu B | C40: 256.5 | D40: 261.1 | E40: 253 | F40: 0.6 | G40: 0.0023 | H40: 637,48K | I40: 0.72222222
B41: Amplifon SpA | C41: 30.37 | D41: 30.49 | E41: 29.33 | F41: 0.33 | G41: 0.011 | H41: 1,11M | I41: 0.73275463
B42: AMS | C42: 19.25 | D42: 19.4 | E42: 18.77 | F42: 0.21 | G42: 0.0113 | H42: 2,50M | I42: 0.73042824
B43: Amundi | C43: 64.95 | D43: 65.1 | E43: 64.25 | F43: 0.35 | G43: 0.0054 | H43: 203,39K | I43: 0.73288194
B44: Andritz Ag | C44: 39.425 | D44: 39.455 | E44: 38.365 | F44: 0.8 | G44: 0.0207 | H44: 0 | I44: 0.7291088
B45: Anglo American | C45: 3.018,5 | D45: 3.020,0 | E45: 2.908,0 | F45: 105 | G45: 0.036 | H45: 2,71M | I45: 0.73263889
B46: Anheuser Busch Inbev | C46: 51.87 | D46: 51.92 | E46: 50.7 | F46: 1.4 | G46: 0.0277 | H46: 1,71M | I46: 0.73585648
B47: Antofagasta | C47: 1.763,00 | D47: 1.764,00 | E47: 1.694,50 | F47: 37 | G47: 0.0214 | H47: 1,27M | I47: 0.73263889
B48: ArcelorMittal | C48: 20.92 | D48: 20.92 | E48: 20.25 | F48: 0.93 | G48: 0.0466 | H48: 8,20M | I48: 0.73420139
B49: Argen-X | C49: 249.6 | D49: 250.8 | E49: 237.2 | F49: 10.6 | G49: 0.0444 | H49: 133,08K | I49: 0.73291667
B50: Arkema | C50: 99.06 | D50: 99.2 | E50: 96.5 | F50: 3.06 | G50: 0.0319 | H50: 225,84K | I50: 0.7328125
B51: Aroundtown | C51: 6.218 | D51: 6.218 | E51: 6.026 | F51: 0.158 | G51: 0.0261 | H51: 9,10K | I51: 0.69444444
B52: Ashmore | C52: 424.2 | D52: 425.6 | E52: 417.2 | F52: 7.8 | G52: 0.0187 | H52: 838,07K | I52: 0.73263889
B53: Ashtead Group | C53: 4.036,0 | D53: 4.057,0 | E53: 3.907,0 | F53: 152 | G53: 0.0391 | H53: 613,06K | I53: 0.73263889
B54: ASM International NV | C54: 207.2 | D54: 209.5 | E54: 200.6 | F54: 5 | G54: 0.0247 | H54: 473,25K | I54: 0.73424769
B55: ASML Holding | C55: 438.85 | D55: 445.3 | E55: 428.2 | F55: 10.4 | G55: 0.0243 | H55: 1,21M | I55: 0.73481481
B56: ASR Nederland | C56: 37.9 | D56: 37.97 | E56: 37.05 | F56: 1.18 | G56: 0.0321 | H56: 567,34K | I56: 0.73515046
B57: Assa Abloy | C57: 235 | D57: 235.2 | E57: 227.6 | F57: 7.2 | G57: 0.0316 | H57: 2,41M | I57: 0.72898148
B58: Assicurazioni Generali | C58: 16.5 | D58: 16.615 | E58: 16.005 | F58: 0.495 | G58: 0.0309 | H58: 8,04M | I58: 0.73490741
B59: Associated British Foods | C59: 2.362,0 | D59: 2.399,0 | E59: 2.325,0 | F59: 6 | G59: 0.0026 | H59: 997,16K | I59: 0.73263889
B60: AstraZeneca | C60: 7.005,0 | D60: 7.023,0 | E60: 6.849,0 | F60: 147 | G60: 0.0214 | H60: 1,94M | I60: 0.73541667
B61: Atlantia | C61: 16 | D61: 16.09 | E61: 15.47 | F61: 0.47 | G61: 0.0299 | H61: 2,23M | I61: 0.73270833
B62: Atlas Copco A | C62: 486.9 | D62: 488.3 | E62: 471.9 | F62: 11.7 | G62: 0.0246 | H62: 1,22M | I62: 0.72914352
B63: Atos | C63: 63.54 | D63: 64.42 | E63: 63.04 | F63: 0.32 | G63: 0.0051 | H63: 613,27K | I63: 0.73270833
B64: Auto Trader Group Plc | C64: 554.6 | D64: 559.6 | E64: 550.4 | F64: 1.4 | G64: 0.0025 | H64: 3,88M | I64: 0.73263889
B65: Avast | C65: 420 | D65: 445.6 | E65: 420 | F65: -26 | G65: -0.0583 | H65: 5,88M | I65: 0.73263889
B66: Aveva | C66: 3.397,0 | D66: 3.425,0 | E66: 3.334,0 | F66: 56 | G66: 0.0168 | H66: 195,54K | I66: 0.73263889
B67: Aviva | C67: 396.7 | D67: 396.9 | E67: 390.9 | F67: 6.3 | G67: 0.0161 | H67: 12,67M | I67: 0.73263889
B68: Axa | C68: 22.57 | D68: 22.64 | E68: 22.1 | F68: 0.56 | G68: 0.0257 | H68: 8,79M | I68: 0.73319444
B69: B&M European Value Retail SA | C69: 520 | D69: 539.8 | E69: 517 | F69: -17.4 | G69: -0.0324 | H69: 3,32M | I69: 0.73263889
B70: BAE Systems | C70: 496.4 | D70: 496.4 | E70: 486.6 | F70: 12.9 | G70: 0.0267 | H70: 5,60M | I70: 0.73263889
B71: Baloise Holding | C71: 168.8 | D71: 168.8 | E71: 165.9 | F71: 4.1 | G71: 0.0249 | H71: 105,24K | I71: 0.73010417
B72: Banco Bpm | C72: 2.293 | D72: 2.306 | E72: 2.228 | F72: 0.089 | G72: 0.0404 | H72: 21,37M | I72: 0.73483796
B73: Banco de Sabadell | C73: 0.479 | D73: 0.479 | E73: 0.451 | F73: 0.032 | G73: 0.0716 | H73: 57,94M | I73: 0.73258102
B74: Bank Ireland | C74: 3.71 | D74: 3.71 | E74: 3.54 | F74: 0.17 | G74: 0.048 | H74: 312,11K | I74: 0.73958333
B75: Bank Pekao S.A. | C75: 72.58 | D75: 72.76 | E75: 70.66 | F75: 1.38 | G75: 0.0194 | H75: 819,44K | I75: 0.69715278
B76: Bankia | C76: 1.737 | D76: 1.74 | E76: 1.706 | F76: 0.045 | G76: 0.0266 | H76: 1,46M | I76: 0.73259259
B77: Bankinter | C77: 5.858 | D77: 5.897 | E77: 5.685 | F77: 0.248 | G77: 0.0442 | H77: 2,43M | I77: 0.73261574
B78: Barclays | C78: 177.92 | D78: 178.18 | E78: 173.28 | F78: 6.34 | G78: 0.0369 | H78: 66,99M | I78: 0.73611111
B79: Barratt Developments | C79: 741 | D79: 741 | E79: 711.8 | F79: 27.6 | G79: 0.0387 | H79: 2,41M | I79: 0.73541667
B80: Barry Callebaut | C80: 2.068,0 | D80: 2.078,0 | E80: 2.040,0 | F80: 18 | G80: 0.0088 | H80: 5,96K | I80: 0.72959491
B81: BASF | C81: 72.77 | D81: 72.85 | E81: 70.84 | F81: 1.92 | G81: 0.0271 | H81: 2,49M | I81: 0.72900463
B82: Bayer | C82: 53.17 | D82: 53.28 | E82: 51.72 | F82: 1.68 | G82: 0.0326 | H82: 1,97M | I82: 0.72899306
B83: BBVA | C83: 4.811 | D83: 4.835 | E83: 4.745 | F83: 0.108 | G83: 0.023 | H83: 10,23M | I83: 0.72899306
B84: Beazley | C84: 362.6 | D84: 367 | E84: 358.2 | F84: 1.4 | G84: 0.0039 | H84: 1,57M | I84: 0.73263889
B85: Bechtle | C85: 156.6 | D85: 158.6 | E85: 153.5 | F85: 3 | G85: 0.0195 | H85: 70,40K | I85: 0.72847222
B86: Beiersdorf | C86: 85.54 | D86: 86.2 | E86: 84.47 | F86: -0.33 | G86: -0.0038 | H86: 293,72K | I86: 0.72896991
B87: Beijer Ref | C87: 368.2 | D87: 368.2 | E87: 356.8 | F87: 8.2 | G87: 0.0228 | H87: 95,83K | I87: 0.72898148
B88: Belimo Holding | C88: 7.200,0 | D88: 7.350,0 | E88: 6.940,0 | F88: 420 | G88: 0.0619 | H88: 1,45K | I88: 0.72959491
B89: Bellway | C89: 3.324,0 | D89: 3.329,0 | E89: 3.168,0 | F89: 165 | G89: 0.0522 | H89: 286,28K | I89: 0.73263889
B90: Berkeley | C90: 4.455,0 | D90: 4.464,0 | E90: 4.305,0 | F90: 150 | G90: 0.0348 | H90: 359,16K | I90: 0.7375
B91: BHP Group | C91: 2.255,00 | D91: 2.257,50 | E91: 2.178,50 | F91: 60.5 | G91: 0.0276 | H91: 4,05M | I91: 0.73263889
B92: Biomerieux | C92: 107.5 | D92: 110.5 | E92: 107.5 | F92: -1.4 | G92: -0.0129 | H92: 190,85K | I92: 0.73273148
B93: BMW | C93: 79.845 | D93: 79.845 | E93: 76.525 | F93: 4.155 | G93: 0.0549 | H93: 1,33M | I93: 0.72900463
B94: BNP Paribas | C94: 53.25 | D94: 53.66 | E94: 51.97 | F94: 1.66 | G94: 0.0322 | H94: 5,23M | I94: 0.73603009
B95: Boliden | C95: 334.1 | D95: 335.3 | E95: 327.7 | F95: 7.6 | G95: 0.0233 | H95: 1,36M | I95: 0.72900463
B96: Bollore | C96: 3.97 | D96: 4.01 | E96: 3.96 | F96: 0.01 | G96: 0.0035 | H96: 1,58M | I96: 0.73271991
B97: Bouygues | C97: 35.25 | D97: 35.34 | E97: 34.66 | F97: 0.78 | G97: 0.0226 | H97: 1,11M | I97: 0.73444444
B98: BP | C98: 318.65 | D98: 324.45 | E98: 312.5 | F98: -0.15 | G98: -0.0005 | H98: 53,59M | I98: 0.73333333
B99: Brenntag AG | C99: 66.24 | D99: 66.48 | E99: 64.48 | F99: 1.94 | G99: 0.0302 | H99: 208,81K | I99: 0.72847222
B100: British American Tobacco | C100: 2.607,5 | D100: 2.630,0 | E100: 2.562,0 | F100: -7 | G100: -0.0027 | H100: 3,37M | I100: 0.73263889
B101: British Land Company | C101: 508.4 | D101: 514.6 | E101: 501 | F101: 1.4 | G101: 0.0028 | H101: 2,45M | I101: 0.73263889
B102: Britvic | C102: 841.5 | D102: 842.5 | E102: 829 | F102: 10.5 | G102: 0.0126 | H102: 380,98K | I102: 0.73819444
B103: BT Group | C103: 137.3 | D103: 141.4 | E103: 135.55 | F103: -4.15 | G103: -0.0293 | H103: 27,83M | I103: 0.73263889
B104: Bunzl | C104: 2.150,0 | D104: 2.191,0 | E104: 2.123,0 | F104: -28 | G104: -0.0129 | H104: 852,59K | I104: 0.73333333
B105: Burberry Group | C105: 1.920,0 | D105: 1.921,5 | E105: 1.850,5 | F105: 55 | G105: 0.0295 | H105: 832,57K | I105: 0.73263889
B106: Bureau Verita | C106: 23.38 | D106: 23.61 | E106: 23.15 | F106: 0.33 | G106: 0.0143 | H106: 1,10M | I106: 0.7327662
B107: Caixabank | C107: 2.553 | D107: 2.553 | E107: 2.5 | F107: 0.083 | G107: 0.0336 | H107: 7,43M | I107: 0.73262731
B108: Campari | C108: 9.7 | D108: 9.758 | E108: 9.45 | F108: 0.206 | G108: 0.0217 | H108: 2,18M | I108: 0.73489583
B109: Capgemini | C109: 139.5 | D109: 139.9 | E109: 136.05 | F109: 3.55 | G109: 0.0261 | H109: 404,12K | I109: 0.73283565
...

Sheet timeSeries
A1: =_xll.Thomson.Reuters.AFOSpreadsheetFormulas.DSGRID(timeSeries!$A$2:$A$435,CONCATENATE("P;MV;DY;ISIN;EPS;WC05476;WC06001;WC03251;WC08001;WC18199;WC01001;WC08366;WC01250;WC02501;WC08301;WC08376;WC02999;WC03998;WC03255;WC08231;WC08221;CODON;ENERDP015;ENERDP018;ENERDP014;ENPIDP079;WC09803;WC09802;WC08416;WC08411;ENERDP024;ENERDP025;ENERDP096;E","NERDP023;ENERDP124;ENERO03V;VOL"),"2005","2018","M","RowHeader=true;ColHeader=true;Heading=true;Code=true;Curn=true;LatestFirstValue=true;SeriesMetaDataLink=true;DispSeriesDescription=false;YearlyTSFormat=false;QuarterlyTSFormat=false;Sym=RIC") -> #NAME?
A2: ='MSCI Europe Net Index EUR End o'!B7 -> TLITn.MI
A3: ='MSCI Europe Net Index EUR End o'!B8 -> B4B.DE
A4: ='MSCI Europe Net Index EUR End o'!B9 -> SESFd.PA
A5: ='MSCI Europe Net Index EUR End o'!B10 -> BMWG_p.DE
A6: ='MSCI Europe Net Index EUR End o'!B11 -> FPEG_p.DE
A7: ='MSCI Europe Net Index EUR End o'!B12 -> LDOF.MI
A8: ='MSCI Europe Net Index EUR End o'!B13 -> TKAG.DE
A9: ='MSCI Europe Net Index EUR End o'!B14 -> ANDR.VI
A10: ='MSCI Europe Net Index EUR End o'!B15 -> BKT.MC
A11: ='MSCI Europe Net Index EUR End o'!B16 -> JCDX.PA
A12: ='MSCI Europe Net Index EUR End o'!B17 -> TNET.BR
A13: ='MSCI Europe Net Index EUR End o'!B18 -> EURA.PA
... A16: ='MSCI Europe Net Index EUR End o'!B21 -> AER.N
A17: ='MSCI Europe Net Index EUR End o'!B22 -> ORNBV.HE | B17: =_xll.Thomson.Reuters.AFOSpreadsheetFormulas.DSGRID(timeSeries!$A$2:$A$435,CONCATENATE("P;MV;DY;ISIN;EPS;WC05476;WC06001;WC03251;WC08001;WC18199;WC01001;WC08366;WC01250;WC02501;WC08301;WC08376;WC02999;WC03998;WC03255;WC08231;WC08221;CODON;ENERDP015;ENERDP018;ENERDP014;ENPIDP079;WC09803;WC09802;WC08416;WC08411;ENERDP024;ENERDP025;ENERDP096;E","NERDP023;ENERDP124;ENERO03V;VOL"),"2005","2018","M","RowHeader=true;ColHeader=true;Heading=true;Code=true;Curn=true;LatestFirstValue=true;SeriesMetaDataLink=true;DispSeriesDescription=false;YearlyTSFormat=false;QuarterlyTSFormat=false;Sym=RIC") -> #NAME?
A18: ='MSCI Europe Net Index EUR End o'!B23 -> SBSTB.OL
A19: ='MSCI Europe Net Index EUR End o'!B24 -> FRAG.DE
A20: ='MSCI Europe Net Index EUR End o'!B25 -> PIRC.MI
A21: ='MSCI Europe Net Index EUR End o'!B26 -> INDUc.ST
A22: ='MSCI Europe Net Index EUR End o'!B27 -> ICAD.PA
A23: ='MSCI Europe Net Index EUR End o'!B28 -> DLGD.L
A24: ='MSCI Europe Net Index EUR End o'!B29 -> ATCA.AS
A25: ='MSCI Europe Net Index EUR End o'!B30 -> WRT1V.HE
A26: ='MSCI Europe Net Index EUR End o'!B31 -> UHRN.S
A27: ='MSCI Europe Net Index EUR End o'!B32 -> VOES.VI
A28: ='MSCI Europe Net Index EUR End o'!B33 -> JMAT.L
A29: ='MSCI Europe Net Index EUR End o'!B34 -> MAP.MC
... A435: ='MSCI Europe Net Index EUR End o'!B440 -> NESN.S
